setup.cfg
setup.py
tests/actions/__init__.py
tests/actions/base_test.py
tests/actions/helper.py
tests/actions/simple_test.py
tests/core/__init__.py
tests/core/helper.py
tests/core/interface_test.py
tests/core/reactor_test.py
tests/filters/__init__.py
tests/filters/base_test.py
tests/functional/__init__.py
tests/functional/functional_tests.py
zmqfirewall/__init__.py
zmqfirewall/exceptions.py
zmqfirewall.egg-info/PKG-INFO
zmqfirewall.egg-info/SOURCES.txt
zmqfirewall.egg-info/dependency_links.txt
zmqfirewall.egg-info/entry_points.txt
zmqfirewall.egg-info/not-zip-safe
zmqfirewall.egg-info/requires.txt
zmqfirewall.egg-info/top_level.txt
zmqfirewall/actions/__init__.py
zmqfirewall/actions/base.py
zmqfirewall/actions/simple.py
zmqfirewall/core/__init__.py
zmqfirewall/core/interface.py
zmqfirewall/core/message.py
zmqfirewall/core/reactor.py
zmqfirewall/filters/__init__.py
zmqfirewall/filters/base.py
zmqfirewall/utils/__init__.py
zmqfirewall/utils/flow_control.py
zmqfirewall/utils/lookup.py