Metadata-Version: 1.0
Name: zmqfirewall
Version: 0.1dev
Summary: Object-based ZeroMQ message repeater/firewall
Home-page: https://github.com/gregjurman/zmqfirewall
Author: Greg Jurman
Author-email: gdj2214@rit.edu
License: MIT
Keywords: zeromq zmq twisted
Platform: UNKNOWN
